blop/__init__.py
blop/_version.py
blop/agent.py
blop/data_access.py
blop/digestion_function.py
blop/dofs.py
blop/objectives.py
blop/plans.py
blop/plotting.py
blop/protocols.py
blop/ax/__init__.py
blop/ax/agent.py
blop/ax/dof.py
blop/ax/objective.py
blop/ax/optimizer.py
blop/bayesian/__init__.py
blop/bayesian/kernels.py
blop/bayesian/models.py
blop/bayesian/acquisition/__init__.py
blop/bayesian/acquisition/analytic.py
blop/bayesian/acquisition/config.yml
blop/bayesian/acquisition/monte_carlo.py
blop/de/__init__.py
blop/de/de_opt_utils.py
blop/de/de_optimization.py
blop/de/hardware_flyer.py
blop/digestion/__init__.py
blop/digestion/tests.py
blop/sim/__init__.py
blop/sim/beamline.py
blop/sim/handlers.py
blop/sim/xrt_beamline.py
blop/sim/xrt_kb_model.py
blop/tests/integration/__init__.py
blop/tests/integration/conftest.py
blop/tests/integration/test_acqfs.py
blop/tests/integration/test_agents.py
blop/tests/integration/test_data_access.py
blop/tests/integration/test_dofs.py
blop/tests/integration/test_pareto.py
blop/tests/integration/test_sims.py
blop/tests/integration/ax/test_ax_agent.py
blop/tests/unit/__init__.py
blop/tests/unit/conftest.py
blop/tests/unit/test_plans.py
blop/tests/unit/ax/__init__.py
blop/tests/unit/ax/test_agent.py
blop/tests/unit/ax/test_dof.py
blop/tests/unit/ax/test_objective.py
blop/tests/unit/ax/test_optimizer.py
blop/utils/__init__.py
blop/utils/functions.py
blop/utils/sets.py
blop-0.9.0.dist-info/METADATA
blop-0.9.0.dist-info/WHEEL
blop-0.9.0.dist-info/licenses/LICENSE
blop-0.9.0.dist-info/RECORD
